agents/__init__.py
agents-1.0.0.dist-info/metadata.json
agents-1.0.0.dist-info/top_level.txt
agents-1.0.0.dist-info/DESCRIPTION.rst
agents-1.0.0.dist-info/WHEEL
agents-1.0.0.dist-info/RECORD
agents-1.0.0.dist-info/METADATA
