Metadata-Version: 2.0
Name: agents
Version: 1.0.0
Summary: Efficient TensorFlow implementation of reinforcement learning algorithms.
Home-page: http://github.com/tensorflow/agents
Author: UNKNOWN
Author-email: UNKNOWN
License: Apache 2.0
Platform: UNKNOWN
Classifier: Programming Language :: Python :: 3 :: Only
Classifier: License :: OSI Approved :: Apache Software License
Classifier: Topic :: Scientific/Engineering :: Artificial Intelligence
Classifier: Intended Audience :: Science/Research
Requires-Dist: tensorflow
Requires-Dist: gym
Requires-Dist: ruamel.yaml
